Metadata-Version: 2.1
Name: hexlet-code609
Version: 0.1.0
Summary: 
Author: Laura609
Author-email: laura.metnietse@gmail.com
Requires-Python: >=3.13,<4.0
Classifier: Programming Language :: Python :: 3
Classifier: Programming Language :: Python :: 3.13
Requires-Dist: prompt (>=0.4.1,<0.5.0)
